Qtica/__init__.py
Qtica/animations/__init__.py
Qtica/animations/animation_group.py
Qtica/animations/property_animation.py
Qtica/core/_IODevice.py
Qtica/core/__init__.py
Qtica/core/_api.py
Qtica/core/_base.py
Qtica/core/_config.py
Qtica/core/_declarative.py
Qtica/core/_icons.py
Qtica/core/_painter.py
Qtica/core/_qobject.py
Qtica/core/_tool.py
Qtica/core/objects/__init__.py
Qtica/core/objects/arg_types.py
Qtica/core/objects/box_layout.py
Qtica/core/objects/pos_events.py
Qtica/core/objects/qss.py
Qtica/core/objects/routes.py
Qtica/core/widgets/__init__.py
Qtica/core/widgets/box_layout.py
Qtica/core/widgets/button.py
Qtica/core/widgets/container.py
Qtica/core/widgets/dialog.py
Qtica/core/widgets/widget.py
Qtica/core/widgets/window.py
Qtica/effects/__init__.py
Qtica/effects/_effects.py
Qtica/effects/box_shadow.py
Qtica/enums/__init__.py
Qtica/enums/colors.py
Qtica/enums/env_vars.py
Qtica/enums/events.py
Qtica/enums/position.py
Qtica/enums/qpa_plugins.py
Qtica/enums/signals.py
Qtica/enums/size.py
Qtica/enums/theme.py
Qtica/enums/widgets.py
Qtica/layouts/__init__.py
Qtica/layouts/border.py
Qtica/layouts/box.py
Qtica/layouts/expand.py
Qtica/layouts/flow.py
Qtica/layouts/form.py
Qtica/layouts/grid.py
Qtica/layouts/stacked.py
Qtica/painters/__init__.py
Qtica/painters/circular_progress.py
Qtica/painters/status_edge.py
Qtica/services/__init__.py
Qtica/services/_methods.py
Qtica/services/clipboard.py
Qtica/services/launche_url.py
Qtica/services/message_handler.py
Qtica/tools/__init__.py
Qtica/tools/action.py
Qtica/tools/color.py
Qtica/tools/copy_progress.py
Qtica/tools/icon.py
Qtica/tools/list_widget_item.py
Qtica/tools/media_player.py
Qtica/tools/movie.py
Qtica/tools/qt_file_open.py
Qtica/tools/qt_svg.py
Qtica/tools/qtcore/__init__.py
Qtica/tools/qtcore/objects.py
Qtica/tools/qtcore/tools.py
Qtica/tools/qtgui/__init__.py
Qtica/tools/qtgui/objects.py
Qtica/tools/qtgui/tools.py
Qtica/tools/qtmultimedia/__init__.py
Qtica/tools/qtmultimedia/objects.py
qtica-0.6.0.dist-info/LICENSE
qtica-0.6.0.dist-info/METADATA
qtica-0.6.0.dist-info/WHEEL
qtica-0.6.0.dist-info/RECORD
