Metadata-Version: 2.1
Name: Qtica
Version: 0.6.0
Summary: Qtica is a Python library that offers a lightweight API built around native PySide6. It enables swift GUI prototyping utilizing contemporary declarative UI methods, all within Python.
Home-page: https://github.com/qtica-project/Qtica
License: GPL-3.0
Keywords: qt,pyside6,python,declarative,qml,Qtica,fast,easy,toolkit,tools
Author: Osama Mohammed Al-zabidi
Author-email: qticaproject@gmail.com
Requires-Python: >=3.10,<3.13
Classifier: License :: OSI Approved :: GNU General Public License v3 (GPLv3)
Classifier: Programming Language :: Python :: 3
Classifier: Programming Language :: Python :: 3.10
Classifier: Programming Language :: Python :: 3.11
Classifier: Programming Language :: Python :: 3.12
Provides-Extra: elusiveicons
Provides-Extra: feathericons
Provides-Extra: fluenticons
Provides-Extra: fontawesomeicons
Provides-Extra: icons
Provides-Extra: materialicons
Provides-Extra: pynput
Requires-Dist: ElusiveIcons (>=2.0,<3.0) ; extra == "elusiveicons" or extra == "icons"
Requires-Dist: FeatherIcons (>=2.0,<3.0) ; extra == "feathericons" or extra == "icons"
Requires-Dist: FluentIcons (>=2.0,<3.0) ; extra == "fluenticons" or extra == "icons"
Requires-Dist: FontawesomeIcons (>=2.0,<3.0) ; extra == "fontawesomeicons" or extra == "icons"
Requires-Dist: MaterialIcons (>=2.0,<3.0) ; extra == "materialicons" or extra == "icons"
Requires-Dist: PySide6 (>=6.5,<6.7)
Requires-Dist: darkdetect (>=0.7)
Requires-Dist: pynput (>=1.7.6,<2.0.0) ; extra == "pynput"
Project-URL: Documentation, https://qticaproject.gitbook.io/qtica
Project-URL: Repository, https://github.com/qtica-project/Qtica
